README.md
setup.cfg
setup.py
yahtzee_envs/__init__.py
yahtzee_envs/constants.py
yahtzee_envs/yahtzee_singleV0.py
yahtzee_envs/yahtzee_singleV1.py
yahtzee_envs/yahtzee_singleV2.py
yahtzee_envs.egg-info/PKG-INFO
yahtzee_envs.egg-info/SOURCES.txt
yahtzee_envs.egg-info/dependency_links.txt
yahtzee_envs.egg-info/requires.txt
yahtzee_envs.egg-info/top_level.txt