Metadata-Version: 1.1
Name: yahtzee-envs
Version: 0.3.0
Summary: A growing collection of environments for         training RL agents and experiementing with various RL methods and        algorithms.
Home-page: https://github.com/tomarbeiter/yahtzee-envs
Author: Tom Arbeiter
Author-email: UNKNOWN
License: Apache 2.0
Platform: UNKNOWN
Classifier: Programming Language :: Python :: 3
Classifier: License :: OSI Approved :: Apache Software License
Classifier: Intended Audience :: Developers
